{
  "card_version": "phase38_v1",
  "generated_at": "2026-01-15T16:14:35.096564+00:00Z",
  "date": "2026-01-15",
  "blocks": {
    "regime": {
      "current_regime": "(no meta regime detected)",
      "confidence": 0.0,
      "has_meta_topics": false,
      "meta_topic_count": 0,
      "basis_type": "NONE"
    },
    "revival": {
      "proposal_count": 1,
      "has_revival": true,
      "loop_warning_count": 1,
      "primary_revival_reason": "New Meta Topics detected (1)"
    },
    "ops": {
      "system_freshness": 87.5,
      "sla_breach_count": 2,
      "has_stale_warning": true,
      "7d_success_rate": "1/7"
    }
  },
  "human_prompt": "현재 Regime 및 데이터 상태를 고려할 때, 이 주제를 오늘 다룰 가치가 있다고 판단하십니까?"
}