{
  "crypto_btc_usd_spot_coingecko": {
    "status": "OK",
    "reason": "Normalized successfully",
    "timestamp": "2026-01-29T04:28:40.318487Z"
  },
  "rates_us10y_fred": {
    "status": "OK",
    "reason": "Normalized successfully",
    "timestamp": "2026-01-29T04:28:41.453860Z"
  },
  "risk_vix_fred": {
    "status": "OK",
    "reason": "Normalized successfully",
    "timestamp": "2026-01-29T04:28:42.096802Z"
  },
  "index_spx_fred": {
    "status": "OK",
    "reason": "Normalized successfully",
    "timestamp": "2026-01-29T04:28:42.282788Z"
  },
  "index_kospi_stooq": {
    "status": "OK",
    "reason": "Normalized successfully",
    "timestamp": "2026-01-29T04:28:42.287623Z"
  },
  "index_nasdaq_fred": {
    "status": "OK",
    "reason": "Normalized successfully",
    "timestamp": "2026-01-29T04:28:43.001572Z"
  },
  "fx_dxy_index_stooq": {
    "status": "OK",
    "reason": "Normalized successfully",
    "timestamp": "2026-01-29T04:28:43.006584Z"
  },
  "rates_us02y_fred": {
    "status": "OK",
    "reason": "Normalized successfully",
    "timestamp": "2026-01-29T04:28:43.899458Z"
  },
  "comm_wti_fred": {
    "status": "OK",
    "reason": "Normalized successfully",
    "timestamp": "2026-01-29T04:28:44.610438Z"
  },
  "metal_platinum_xptusd_stooq": {
    "status": "OK",
    "reason": "Normalized successfully",
    "timestamp": "2026-01-29T04:28:44.613739Z"
  },
  "metal_gold_paxg_coingecko": {
    "status": "OK",
    "reason": "Normalized successfully",
    "timestamp": "2026-01-29T04:28:44.617296Z"
  },
  "metal_silver_kag_coingecko": {
    "status": "OK",
    "reason": "Normalized successfully",
    "timestamp": "2026-01-29T04:28:44.624396Z"
  },
  "crypto_eth_usd_spot_coingecko": {
    "status": "OK",
    "reason": "Normalized successfully",
    "timestamp": "2026-01-29T04:28:44.627796Z"
  },
  "rates_kor_base_rate_ecos": {
    "status": "OK",
    "reason": "Normalized successfully",
    "timestamp": "2026-01-29T04:28:44.635480Z"
  },
  "inflation_kor_cpi_ecos": {
    "status": "OK",
    "reason": "Normalized successfully",
    "timestamp": "2026-01-29T04:28:44.641966Z"
  },
  "fx_usdkrw_ecos": {
    "status": "OK",
    "reason": "Normalized successfully",
    "timestamp": "2026-01-29T04:28:44.697969Z"
  },
  "rates_fed_funds_fred": {
    "status": "OK",
    "reason": "Normalized successfully",
    "timestamp": "2026-01-29T04:28:44.760124Z"
  },
  "inflation_cpi_fred": {
    "status": "OK",
    "reason": "Normalized successfully",
    "timestamp": "2026-01-29T04:28:44.827380Z"
  },
  "inflation_pce_fred": {
    "status": "OK",
    "reason": "Normalized successfully",
    "timestamp": "2026-01-29T04:28:44.886702Z"
  },
  "liquidity_m2_fred": {
    "status": "OK",
    "reason": "Normalized successfully",
    "timestamp": "2026-01-29T04:28:44.946153Z"
  },
  "employment_unrate_fred": {
    "status": "OK",
    "reason": "Normalized successfully",
    "timestamp": "2026-01-29T04:28:45.014733Z"
  },
  "credit_hy_spread_fred": {
    "status": "OK",
    "reason": "Normalized successfully",
    "timestamp": "2026-01-29T04:28:45.535396Z"
  },
  "risk_financial_stress_fred": {
    "status": "OK",
    "reason": "Normalized successfully",
    "timestamp": "2026-01-29T04:28:45.639236Z"
  },
  "derived_yield_curve_10y_2y": {
    "status": "OK",
    "reason": "Normalized successfully",
    "timestamp": "2026-01-29T04:28:45.639715Z"
  },
  "derived_gold_silver_ratio": {
    "status": "OK",
    "reason": "Normalized successfully",
    "timestamp": "2026-01-29T04:28:45.639733Z"
  },
  "struct_dart_cb_bw": {
    "status": "OK",
    "reason": "Normalized successfully",
    "timestamp": "2026-01-29T04:28:45.640741Z"
  },
  "struct_dart_disposal": {
    "status": "OK",
    "reason": "Normalized successfully",
    "timestamp": "2026-01-29T04:28:45.640787Z"
  },
  "struct_krx_foreigner_flow": {
    "status": "OK",
    "reason": "Normalized successfully",
    "timestamp": "2026-01-29T04:28:45.640833Z"
  },
  "real_estate_price_index": {
    "status": "OK",
    "reason": "Normalized successfully",
    "timestamp": "2026-01-29T04:28:45.641788Z"
  },
  "real_estate_volume": {
    "status": "OK",
    "reason": "Normalized successfully",
    "timestamp": "2026-01-29T04:28:45.641824Z"
  },
  "real_estate_unsold": {
    "status": "OK",
    "reason": "Normalized successfully",
    "timestamp": "2026-01-29T04:28:45.641859Z"
  }
}