{
  "crypto_btc_usd_spot_coingecko": {
    "status": "OK",
    "reason": "Normalized successfully",
    "timestamp": "2026-02-04T12:08:11.452686Z"
  },
  "rates_us10y_fred": {
    "status": "OK",
    "reason": "Normalized successfully",
    "timestamp": "2026-02-04T12:08:12.374466Z"
  },
  "risk_vix_fred": {
    "status": "OK",
    "reason": "Normalized successfully",
    "timestamp": "2026-02-04T12:08:12.866432Z"
  },
  "index_spx_fred": {
    "status": "OK",
    "reason": "Normalized successfully",
    "timestamp": "2026-02-04T12:08:13.007681Z"
  },
  "index_kospi_stooq": {
    "status": "OK",
    "reason": "Normalized successfully",
    "timestamp": "2026-02-04T12:08:13.012592Z"
  },
  "index_nasdaq_fred": {
    "status": "OK",
    "reason": "Normalized successfully",
    "timestamp": "2026-02-04T12:08:13.559908Z"
  },
  "fx_dxy_index_stooq": {
    "status": "OK",
    "reason": "Normalized successfully",
    "timestamp": "2026-02-04T12:08:13.564213Z"
  },
  "rates_us02y_fred": {
    "status": "OK",
    "reason": "Normalized successfully",
    "timestamp": "2026-02-04T12:08:14.241133Z"
  },
  "comm_wti_fred": {
    "status": "OK",
    "reason": "Normalized successfully",
    "timestamp": "2026-02-04T12:08:14.787585Z"
  },
  "metal_platinum_xptusd_stooq": {
    "status": "OK",
    "reason": "Normalized successfully",
    "timestamp": "2026-02-04T12:08:14.790675Z"
  },
  "metal_gold_paxg_coingecko": {
    "status": "OK",
    "reason": "Normalized successfully",
    "timestamp": "2026-02-04T12:08:14.794161Z"
  },
  "metal_silver_kag_coingecko": {
    "status": "OK",
    "reason": "Normalized successfully",
    "timestamp": "2026-02-04T12:08:14.800958Z"
  },
  "crypto_eth_usd_spot_coingecko": {
    "status": "OK",
    "reason": "Normalized successfully",
    "timestamp": "2026-02-04T12:08:14.803962Z"
  },
  "rates_kor_base_rate_ecos": {
    "status": "OK",
    "reason": "Normalized successfully",
    "timestamp": "2026-02-04T12:08:14.810180Z"
  },
  "inflation_kor_cpi_ecos": {
    "status": "OK",
    "reason": "Normalized successfully",
    "timestamp": "2026-02-04T12:08:14.815558Z"
  },
  "fx_usdkrw_ecos": {
    "status": "OK",
    "reason": "Normalized successfully",
    "timestamp": "2026-02-04T12:08:14.863439Z"
  },
  "rates_fed_funds_fred": {
    "status": "OK",
    "reason": "Normalized successfully",
    "timestamp": "2026-02-04T12:08:14.912789Z"
  },
  "inflation_cpi_fred": {
    "status": "OK",
    "reason": "Normalized successfully",
    "timestamp": "2026-02-04T12:08:14.966479Z"
  },
  "inflation_pce_fred": {
    "status": "OK",
    "reason": "Normalized successfully",
    "timestamp": "2026-02-04T12:08:15.012936Z"
  },
  "liquidity_m2_fred": {
    "status": "OK",
    "reason": "Normalized successfully",
    "timestamp": "2026-02-04T12:08:15.059708Z"
  },
  "employment_unrate_fred": {
    "status": "OK",
    "reason": "Normalized successfully",
    "timestamp": "2026-02-04T12:08:15.113459Z"
  },
  "credit_hy_spread_fred": {
    "status": "OK",
    "reason": "Normalized successfully",
    "timestamp": "2026-02-04T12:08:15.521327Z"
  },
  "risk_financial_stress_fred": {
    "status": "OK",
    "reason": "Normalized successfully",
    "timestamp": "2026-02-04T12:08:15.603120Z"
  },
  "derived_yield_curve_10y_2y": {
    "status": "OK",
    "reason": "Normalized successfully",
    "timestamp": "2026-02-04T12:08:15.603547Z"
  },
  "derived_gold_silver_ratio": {
    "status": "OK",
    "reason": "Normalized successfully",
    "timestamp": "2026-02-04T12:08:15.603562Z"
  },
  "struct_dart_cb_bw": {
    "status": "OK",
    "reason": "Normalized successfully",
    "timestamp": "2026-02-04T12:08:15.604388Z"
  },
  "struct_dart_disposal": {
    "status": "OK",
    "reason": "Normalized successfully",
    "timestamp": "2026-02-04T12:08:15.604420Z"
  },
  "struct_krx_foreigner_flow": {
    "status": "OK",
    "reason": "Normalized successfully",
    "timestamp": "2026-02-04T12:08:15.604444Z"
  },
  "real_estate_price_index": {
    "status": "OK",
    "reason": "Normalized successfully",
    "timestamp": "2026-02-04T12:08:15.605178Z"
  },
  "real_estate_volume": {
    "status": "OK",
    "reason": "Normalized successfully",
    "timestamp": "2026-02-04T12:08:15.605207Z"
  },
  "real_estate_unsold": {
    "status": "OK",
    "reason": "Normalized successfully",
    "timestamp": "2026-02-04T12:08:15.605228Z"
  }
}